planterbox_webdriver/__init__.py
planterbox_webdriver/css_selector_steps.py
planterbox_webdriver/jquery-2.2.0.min.js
planterbox_webdriver/monkeypatch.py
planterbox_webdriver/screenshot.py
planterbox_webdriver/util.py
planterbox_webdriver/webdriver.py
planterbox_webdriver/tests/__init__.py
planterbox_webdriver/tests/html_pages/__init__.py
planterbox_webdriver/tests/test_css_selector_steps/__init__.py
planterbox_webdriver/tests/test_screenshot/__init__.py
planterbox_webdriver/tests/test_unicode/__init__.py
planterbox_webdriver/tests/test_webdriver/__init__.py
planterbox_webdriver/tests/test_webdriver/test_failures.py
planterbox_webdriver-0.5.0.dist-info/LICENSE
planterbox_webdriver-0.5.0.dist-info/METADATA
planterbox_webdriver-0.5.0.dist-info/WHEEL
planterbox_webdriver-0.5.0.dist-info/top_level.txt
planterbox_webdriver-0.5.0.dist-info/zip-safe
planterbox_webdriver-0.5.0.dist-info/RECORD
