Metadata-Version: 2.1
Name: planterbox-webdriver
Version: 0.5.0
Summary: Steps for web testing using selenium and planterbox
Home-page: https://github.com/npilon/planterbox-webdriver
Author: Nick Pilon
Author-email: npilon@gmail.com
License: UNKNOWN
Keywords: testing test bdd lettuce cucumber gherkin nosetests nose2 webdriver selenium
Platform: UNKNOWN
Classifier: Intended Audience :: Developers
Classifier: Programming Language :: Python
Classifier: Topic :: Internet :: WWW/HTTP
Classifier: Topic :: Software Development :: Testing
Requires-Dist: planterbox (>=0.6.3)
Requires-Dist: selenium (>=4.0.0)
Requires-Dist: six
